textfield_parser/__init__.py
textfield_parser/textfield_parser.py
textfield_parser/textfield_parser_2.py
textfield_parser-0.0.29.dist-info/LICENSE
textfield_parser-0.0.29.dist-info/METADATA
textfield_parser-0.0.29.dist-info/WHEEL
textfield_parser-0.0.29.dist-info/top_level.txt
textfield_parser-0.0.29.dist-info/RECORD
