Metadata-Version: 2.1
Name: textfield-parser
Version: 0.0.29
Summary: Parsing Textfields
Home-page: https://github.com/thhapke/textfield_parser
Author: Thorsten Hapke
Author-email: thorsten.hapke@sap.com
License: UNKNOWN
Keywords: textfield parsing
Platform: UNKNOWN
Classifier: Programming Language :: Python :: 3.5
Classifier: Programming Language :: Python :: 3.6
Classifier: Programming Language :: Python :: 3.7
Classifier: License :: OSI Approved :: MIT License
Classifier: Operating System :: OS Independent
